[
  {
    "ruleId": "jsonc/sort-keys",
    "severity": 2,
    "message": "Expected object keys to be in specified order. 'bin' should be before 'devDependencies'.",
    "messageId": "sortKeys"
  },
  {
    "ruleId": "jsonc/sort-keys",
    "severity": 2,
    "message": "Expected object keys to be in specified order. 'bugs' should be before 'peerDependencies'.",
    "messageId": "sortKeys"
  },
  {
    "ruleId": "jsonc/sort-keys",
    "severity": 2,
    "message": "Expected object keys to be in specified order. 'engines' should be before 'dependencies'.",
    "messageId": "sortKeys"
  },
  {
    "ruleId": "jsonc/sort-keys",
    "severity": 2,
    "message": "Expected object keys to be in specified order. 'exports' should be before 'peerDependenciesMeta'.",
    "messageId": "sortKeys"
  },
  {
    "ruleId": "jsonc/sort-keys",
    "severity": 2,
    "message": "Expected object keys to be in specified order. 'categories' should be before 'husky'.",
    "messageId": "sortKeys"
  },
  {
    "ruleId": "jsonc/sort-keys",
    "severity": 2,
    "message": "Expected object keys to be in specified order. 'repository' should be before 'categories'.",
    "messageId": "sortKeys"
  },
  {
    "ruleId": "jsonc/sort-keys",
    "severity": 2,
    "message": "Expected object keys to be in specified order. 'typesVersions' should be before 'scripts'.",
    "messageId": "sortKeys"
  },
  {
    "ruleId": "jsonc/sort-keys",
    "severity": 2,
    "message": "Expected object keys to be in specified order. 'license' should be before 'eslintConfig'.",
    "messageId": "sortKeys"
  }
]
